xcgui/__init__.py
xcgui/_xcgui.cp313-win_amd64.pyd
xcgui/_xcgui.pyi
xcgui/decorators.py
xcgui-0.1.9.dist-info/licenses/LICENSE
xcgui-0.1.9.dist-info/METADATA
xcgui-0.1.9.dist-info/WHEEL
xcgui-0.1.9.dist-info/top_level.txt
xcgui-0.1.9.dist-info/RECORD
