Metadata-Version: 2.4
Name: xcgui
Version: 0.1.9
Summary: xcgui - bundled xcgui for python
Author-email: evilbeast <houshao55@gmail.com>
License-Expression: MIT
Project-URL: Homepage, https://github.com/smallevilbeast/pyxcgui
Project-URL: Repository, https://github.com/smallevilbeast/pyxcgui
Keywords: xcgui,pybind11,ui
Classifier: Development Status :: 4 - Beta
Classifier: Programming Language :: Python :: 3.9
Classifier: Programming Language :: Python :: 3.10
Classifier: Programming Language :: Python :: 3.11
Classifier: Programming Language :: Python :: 3.12
Classifier: Programming Language :: Python :: 3.13
Classifier: Programming Language :: Python :: 3.14
Requires-Python: >=3.9
License-File: LICENSE
Provides-Extra: dev
Requires-Dist: pybind11-stubgen>=2.5.5; extra == "dev"
Requires-Dist: build>=0.10.0; extra == "dev"
Requires-Dist: twine>=4.0.0; extra == "dev"
Requires-Dist: cibuildwheel>=2.16.0; extra == "dev"
Dynamic: license-file
